README.md
setup.py
mongodb_to_other/__init__.py
mongodb_to_other.egg-info/PKG-INFO
mongodb_to_other.egg-info/SOURCES.txt
mongodb_to_other.egg-info/dependency_links.txt
mongodb_to_other.egg-info/top_level.txt