Metadata-Version: 2.1
Name: mongodb-to-other
Version: 0.1.3
Summary: 将mongodb导出为其他
Home-page: https://github.com/zyzlaozhang/mongodb_to_other
Author: zyzlaozhang2011
Author-email: zyzlaozhang2011@163.com
License: MIT
Classifier: License :: OSI Approved :: MIT License
Classifier: Programming Language :: Python
Classifier: Programming Language :: Python :: 3
Classifier: Programming Language :: Python :: 3.6
Classifier: Programming Language :: Python :: Implementation :: CPython
Classifier: Programming Language :: Python :: Implementation :: PyPy
Requires-Python: >=3.6.0
